sharpify/__init__.py
sharpify/sharpify.js
sharpify/sharpify.py
sharpify-0.1.4.dist-info/LICENSE
sharpify-0.1.4.dist-info/METADATA
sharpify-0.1.4.dist-info/WHEEL
sharpify-0.1.4.dist-info/top_level.txt
sharpify-0.1.4.dist-info/RECORD
