Metadata-Version: 2.1
Name: sharpify
Version: 0.1.4
Summary: Turn the flask routing / architecture into Asp.Net Core like
Home-page: UNKNOWN
Author: Ricki
Author-email: 
License: MIT
Platform: UNKNOWN
Requires-Dist: Flask
